unix_fs_exporter/__init__.py
unix_fs_exporter/content.py
unix_fs_exporter/exporter.py
unix_fs_exporter/py.typed
unix_fs_exporter/resolvers.py
unix_fs_exporter/ipfs_dag_pb/__init__.py
unix_fs_exporter/ipfs_dag_pb/dag_pb.py
unix_fs_exporter/ipfs_dag_pb/dag_pb_pb2.py
unix_fs_exporter/ipfs_unix_fs/__init__.py
unix_fs_exporter/ipfs_unix_fs/unix_fs.py
unix_fs_exporter/ipfs_unix_fs/unixfs_pb2.py
unix_fs_exporter-0.2.0.dist-info/METADATA
unix_fs_exporter-0.2.0.dist-info/WHEEL
unix_fs_exporter-0.2.0.dist-info/top_level.txt
unix_fs_exporter-0.2.0.dist-info/RECORD
